{
  "db_name": "PostgreSQL",
  "query": "\n        SELECT id, public_id, email, username, password_hash, created_at, updated_at\n        FROM users\n        WHERE id = $1\n        ",
  "describe": {
    "columns": [
      {
        "ordinal": 0,
        "name": "id",
        "type_info": "Uuid"
      },
      {
        "ordinal": 1,
        "name": "public_id",
        "type_info": "Varchar"
      },
      {
        "ordinal": 2,
        "name": "email",
        "type_info": "Varchar"
      },
      {
        "ordinal": 3,
        "name": "username",
        "type_info": "Varchar"
      },
      {
        "ordinal": 4,
        "name": "password_hash",
        "type_info": "Varchar"
      },
      {
        "ordinal": 5,
        "name": "created_at",
        "type_info": "Timestamptz"
      },
      {
        "ordinal": 6,
        "name": "updated_at",
        "type_info": "Timestamptz"
      }
    ],
    "parameters": {
      "Left": [
        "Uuid"
      ]
    },
    "nullable": [
      false,
      false,
      false,
      false,
      false,
      false,
      false
    ]
  },
  "hash": "e0ff97db4970aa41a22662f9b117e5d81505bff10ab782584f192438ae88cb2d"
}
